mahiru/__main__.py
mahiru-0.0.2.dist-info/METADATA
mahiru-0.0.2.dist-info/WHEEL
mahiru-0.0.2.dist-info/top_level.txt
mahiru-0.0.2.dist-info/RECORD
